emioapi/__init__.py
emioapi/_camerafeedwindow.py
emioapi/_depthcamera.py
emioapi/_emiomotorsparameters.py
emioapi/_motorgroup.py
emioapi/cameraparameter.json
emioapi/emioapi.py
emioapi/emiocamera.py
emioapi/emiomotors.py
emioapi/multiprocessemiocamera.py
emioapi-0.1.1.dist-info/licenses/LICENSE.txt
emioapi-0.1.1.dist-info/METADATA
emioapi-0.1.1.dist-info/WHEEL
emioapi-0.1.1.dist-info/top_level.txt
emioapi-0.1.1.dist-info/RECORD
