Metadata-Version: 2.4
Name: emioapi
Version: 0.1.1
Summary: An API for controlling  the motors of the EMIO robot.
Author-email: Compliance Robotics <support@compliance-robotics.com>
Project-URL: Repository, https://github.com/SofaComplianceRobotics/Emio.API
Keywords: roboticsc,emio,api
Requires-Python: >=3.10
License-File: LICENSE.txt
Requires-Dist: pyserial
Requires-Dist: dynamixel_sdk
Requires-Dist: pyrealsense2; platform_system != "Darwin"
Requires-Dist: pyrealsense2-macosx; platform_system == "Darwin"
Requires-Dist: opencv-python
Requires-Dist: numpy==1.26.4
Requires-Dist: pillow
Dynamic: license-file
